manim_dsa/__init__.py
manim_dsa/constants.py
manim_dsa/fonts/CascadiaCode.ttf
manim_dsa/m_collection/__init__.py
manim_dsa/m_collection/m_array.py
manim_dsa/m_collection/m_collection.py
manim_dsa/m_collection/m_stack.py
manim_dsa/m_graph/__init__.py
manim_dsa/m_graph/m_graph.py
manim_dsa/m_graph/m_tree.py
manim_dsa/m_variable/__init__.py
manim_dsa/m_variable/m_variable.py
manim_dsa/utils/__init__.py
manim_dsa/utils/utils.py
manim_dsa-0.4.0.dist-info/METADATA
manim_dsa-0.4.0.dist-info/WHEEL
manim_dsa-0.4.0.dist-info/RECORD
