Metadata-Version: 2.4
Name: manim-dsa
Version: 0.4.0
Summary: A Manim plugin to animate common data structures.
Project-URL: repository, https://github.com/F4bbi/manim-dsa
Project-URL: documentation, https://manim-dsa.readthedocs.io/
Author-email: Fabio Missagia <fabio.missagia@gmail.com>
License-Expression: MIT
Requires-Python: >=3.9
Requires-Dist: manim>=0.19.0
